DaMo/__init__.py
DaMo/dmInit.py
DaMo/dmMoustKey.py
DaMo/dmPic.py
DaMo/dmSystem.py
DaMo/dmWindows.py
DaMo/err.py
DaMo/func.py
PyDaMo-0.1.0.dist-info/METADATA
PyDaMo-0.1.0.dist-info/WHEEL
PyDaMo-0.1.0.dist-info/top_level.txt
PyDaMo-0.1.0.dist-info/RECORD
