Metadata-Version: 2.1
Name: PyDaMo
Version: 0.1.0
Summary: Interop.SHDocVw
Home-page: https://code.aliyun.com/a1403951401/PyDaMo
Author: Martin
Author-email: 1403951401@qq.com
License: UNKNOWN
Platform: UNKNOWN
Classifier: Programming Language :: Python :: 3
Classifier: License :: OSI Approved :: MIT License
Classifier: Operating System :: OS Independent
Requires-Python: >=3.6
